openhive/__init__.py
openhive/agent.py
openhive/agent_config.py
openhive/agent_error.py
openhive/agent_identity.py
openhive/agent_registry.py
openhive/agent_server.py
openhive/agent_signature.py
openhive/log.py
openhive/query_parser.py
openhive/remote_registry.py
openhive/types.py
openhive-0.8.15.dist-info/licenses/LICENSE.md
openhive-0.8.15.dist-info/METADATA
openhive-0.8.15.dist-info/WHEEL
openhive-0.8.15.dist-info/top_level.txt
openhive-0.8.15.dist-info/RECORD
