Metadata-Version: 2.4
Name: openhive
Version: 0.8.15
Summary: Core library for implementing H.I.V.E. Protocol compliant agents in Python
Author-email: OpenHive Team <team@openhive.sh>
Project-URL: Homepage, https://github.com/openhivestack/python-sdk
Project-URL: Issues, https://github.com/openhivestack/python-sdk/issues
Classifier: Programming Language :: Python :: 3
Classifier: License :: OSI Approved :: GNU Affero General Public License v3 or later (AGPLv3+)
Classifier: Operating System :: OS Independent
Requires-Python: >=3.8
License-File: LICENSE.md
Requires-Dist: pydantic>=2.5.3
Requires-Dist: pyyaml>=6.0.1
Requires-Dist: pynacl>=1.5.0
Requires-Dist: fastapi>=0.109.0
Requires-Dist: uvicorn>=0.27.0.post1
Requires-Dist: python-dotenv>=1.0.1
Requires-Dist: httpx>=0.26.0
Requires-Dist: yarl>=1.9.4
Requires-Dist: jinja2>=3.1.3
Requires-Dist: canonicaljson>=2.0.0
Requires-Dist: cryptography
Requires-Dist: colorlog>=6.8.2
Dynamic: license-file
